src/args.py
src/color.py
src/log.py
src/main.py
arduino_oxidizer-1.0.0.dist-info/METADATA
arduino_oxidizer-1.0.0.dist-info/WHEEL
arduino_oxidizer-1.0.0.dist-info/entry_points.txt
arduino_oxidizer-1.0.0.dist-info/top_level.txt
arduino_oxidizer-1.0.0.dist-info/RECORD
