Metadata-Version: 2.1
Name: arduino-oxidizer
Version: 1.0.0
Summary: A python tool to build Rust project for Arduino and write it.
Home-page: https://github.com/loxygenK/oxidizer
Author: loxygen
Author-email: me@loxygen.dev
Maintainer: loxygen
Maintainer-email: me@loxygen.dev
License: MIT
Platform: UNKNOWN
Classifier: Programming Language :: Python :: 3
Classifier: Programming Language :: Python :: 3.8
Classifier: Programming Language :: Rust
Classifier: Topic :: Software Development :: Build Tools
Classifier: Topic :: Software Development :: Embedded Systems
Classifier: License :: OSI Approved :: MIT License
Requires-Dist: toml (~=0.10)
Requires-Dist: pyserial (~=3.5)
